{
  "timestamp": "2025-03-29 18:12:16",
  "num_objects": 5,
  "processing_time_seconds": 0.001055002212524414,
  "objects": [
    {
      "class_name": "chair",
      "confidence": 0,
      "servo_angles": {
        "x_servo": 64,
        "y_servo": 171
      },
      "pattern_file": "",
      "is_cached": false
    },
    {
      "class_name": "person",
      "confidence": 0,
      "servo_angles": {
        "x_servo": 51,
        "y_servo": 137
      },
      "pattern_file": "",
      "is_cached": false
    },
    {
      "class_name": "cup",
      "confidence": 0,
      "servo_angles": {
        "x_servo": 39,
        "y_servo": 126
      },
      "pattern_file": "",
      "is_cached": false
    },
    {
      "class_name": "laptop",
      "confidence": 0,
      "servo_angles": {
        "x_servo": 21,
        "y_servo": 223
      },
      "pattern_file": "",
      "is_cached": false
    },
    {
      "class_name": "chair",
      "confidence": 0,
      "servo_angles": {
        "x_servo": 85,
        "y_servo": 124
      },
      "pattern_file": "",
      "is_cached": false
    }
  ],
  "summary": {
    "sentence": "I see a person on the left bottom, a cup on the left bottom, 2 chairs in the center bottom, and a laptop on the left bottom.",
    "avg_x_servo": 52.0,
    "avg_y_servo": 156.2,
    "pattern_file": "",
    "is_cached": false
  }
}